neuroconv/__init__.py
neuroconv/basedatainterface.py
neuroconv/baseextractorinterface.py
neuroconv/basetemporalalignmentinterface.py
neuroconv/nwbconverter.py
neuroconv/converters/__init__.py
neuroconv/datainterfaces/__init__.py
neuroconv/datainterfaces/behavior/__init__.py
neuroconv/datainterfaces/behavior/audio/__init__.py
neuroconv/datainterfaces/behavior/audio/audiointerface.py
neuroconv/datainterfaces/behavior/deeplabcut/__init__.py
neuroconv/datainterfaces/behavior/deeplabcut/_dlc_utils.py
neuroconv/datainterfaces/behavior/deeplabcut/deeplabcutdatainterface.py
neuroconv/datainterfaces/behavior/fictrac/__init__.py
neuroconv/datainterfaces/behavior/fictrac/fictracdatainterface.py
neuroconv/datainterfaces/behavior/lightningpose/__init__.py
neuroconv/datainterfaces/behavior/lightningpose/lightningposeconverter.py
neuroconv/datainterfaces/behavior/lightningpose/lightningposedatainterface.py
neuroconv/datainterfaces/behavior/medpc/__init__.py
neuroconv/datainterfaces/behavior/medpc/medpc_helpers.py
neuroconv/datainterfaces/behavior/medpc/medpcdatainterface.py
neuroconv/datainterfaces/behavior/miniscope/__init__.py
neuroconv/datainterfaces/behavior/miniscope/miniscopedatainterface.py
neuroconv/datainterfaces/behavior/miniscope/miniscopeheadorientationinterface.py
neuroconv/datainterfaces/behavior/neuralynx/__init__.py
neuroconv/datainterfaces/behavior/neuralynx/neuralynx_nvt_interface.py
neuroconv/datainterfaces/behavior/neuralynx/nvt_utils.py
neuroconv/datainterfaces/behavior/sleap/__init__.py
neuroconv/datainterfaces/behavior/sleap/sleap_utils.py
neuroconv/datainterfaces/behavior/sleap/sleapdatainterface.py
neuroconv/datainterfaces/behavior/video/__init__.py
neuroconv/datainterfaces/behavior/video/externalvideointerface.py
neuroconv/datainterfaces/behavior/video/internalvideointerface.py
neuroconv/datainterfaces/behavior/video/video_utils.py
neuroconv/datainterfaces/behavior/video/videodatainterface.py
neuroconv/datainterfaces/ecephys/__init__.py
neuroconv-0.9.0.dist-info/METADATA
neuroconv-0.9.0.dist-info/WHEEL
neuroconv-0.9.0.dist-info/entry_points.txt
neuroconv-0.9.0.dist-info/top_level.txt
neuroconv-0.9.0.dist-info/RECORD
