Metadata-Version: 2.4
Name: neuroconv
Version: 0.9.0
Summary: Convert data from proprietary formats to NWB format.
Author: Cody Baker, Szonja Weigl, Heberto Mayorquin, Paul Adkisson, Luiz Tauffer, Alessandra Trapani
Author-email: Ben Dichter <ben.dichter@catalystneuro.com>
License: BSD 3-Clause License
Project-URL: Homepage, https://github.com/catalystneuro/neuroconv
Project-URL: Documentation, https://neuroconv.readthedocs.io/
Project-URL: Changelog, https://github.com/catalystneuro/neuroconv/blob/main/CHANGELOG.md
Keywords: nwb,NeurodataWithoutBorders
Classifier: Intended Audience :: Science/Research
Classifier: Programming Language :: Python :: 3.10
Classifier: Programming Language :: Python :: 3.11
Classifier: Programming Language :: Python :: 3.12
Classifier: Programming Language :: Python :: 3.13
Classifier: Operating System :: POSIX :: Linux
Classifier: Operating System :: Microsoft :: Windows
Classifier: Operating System :: MacOS
Classifier: License :: OSI Approved :: BSD License
Requires-Python: >=3.10
Requires-Dist: numpy>=1.22.0; python_version <= "3.11"
Requires-Dist: numpy>=1.26.0; python_version >= "3.12"
Requires-Dist: PyYAML>=5.4
Requires-Dist: h5py>=3.9.0
Requires-Dist: hdmf>=4.1.1
Requires-Dist: hdmf_zarr>=0.11
Requires-Dist: pynwb>=3.0.0
Requires-Dist: pydantic>=2.0
Requires-Dist: typing_extensions>=4.1.0
Requires-Dist: psutil>=5.8.0
Requires-Dist: tqdm>=4.60.0
Requires-Dist: pandas
Requires-Dist: parse>=1.20.0
Requires-Dist: click
Requires-Dist: jsonschema>=3.2.0
Requires-Dist: docstring-parser
Requires-Dist: packaging
Requires-Dist: referencing
Requires-Dist: numcodecs<0.16.0
Provides-Extra: sorting-analyzer
Requires-Dist: scipy; extra == "sorting-analyzer"
Provides-Extra: dandi
Requires-Dist: dandi>=0.70.0; extra == "dandi"
Provides-Extra: compressors
Requires-Dist: hdf5plugin; extra == "compressors"
Provides-Extra: aws
Requires-Dist: boto3; extra == "aws"
Provides-Extra: csv
Provides-Extra: excel
Requires-Dist: openpyxl; extra == "excel"
Requires-Dist: xlrd; extra == "excel"
Provides-Extra: text
Requires-Dist: neuroconv[csv]; extra == "text"
Requires-Dist: neuroconv[excel]; extra == "text"
Provides-Extra: audio
Requires-Dist: ndx-sound>=0.2.2; extra == "audio"
Requires-Dist: scipy; extra == "audio"
Provides-Extra: sleap
Requires-Dist: av>=10.0.0; extra == "sleap"
Requires-Dist: sleap-io>=0.5.2; extra == "sleap"
Requires-Dist: ndx-pose>=0.2.2; extra == "sleap"
Provides-Extra: deeplabcut
Requires-Dist: ndx-pose>=0.2; extra == "deeplabcut"
Requires-Dist: tables; platform_system != "Darwin" and extra == "deeplabcut"
Requires-Dist: tables>=3.10.1; (platform_system == "Darwin" and python_version >= "3.10") and extra == "deeplabcut"
Provides-Extra: fictrac
Provides-Extra: video
Requires-Dist: opencv-python-headless>=4.8.1.78; extra == "video"
Provides-Extra: lightningpose
Requires-Dist: ndx-pose>=0.2; extra == "lightningpose"
Requires-Dist: neuroconv[video]; extra == "lightningpose"
Provides-Extra: medpc
Requires-Dist: ndx-events==0.2.1; extra == "medpc"
Provides-Extra: behavior
Requires-Dist: neuroconv[sleap]; extra == "behavior"
Requires-Dist: neuroconv[audio]; extra == "behavior"
Requires-Dist: neuroconv[deeplabcut]; extra == "behavior"
Requires-Dist: neuroconv[fictrac]; extra == "behavior"
Requires-Dist: neuroconv[video]; extra == "behavior"
Requires-Dist: neuroconv[lightningpose]; extra == "behavior"
Requires-Dist: neuroconv[medpc]; extra == "behavior"
Requires-Dist: ndx-miniscope>=0.5.1; extra == "behavior"
Provides-Extra: ecephys-minimal
Requires-Dist: spikeinterface>=0.103.0; extra == "ecephys-minimal"
Requires-Dist: neo>=0.14.3; extra == "ecephys-minimal"
Provides-Extra: alphaomega
Requires-Dist: neuroconv[ecephys_minimal]; extra == "alphaomega"
Provides-Extra: axon
Requires-Dist: neuroconv[ecephys_minimal]; extra == "axon"
Provides-Extra: axona
Requires-Dist: neuroconv[ecephys_minimal]; extra == "axona"
Provides-Extra: biocam
Requires-Dist: neuroconv[ecephys_minimal]; extra == "biocam"
Provides-Extra: blackrock
Requires-Dist: neuroconv[ecephys_minimal]; extra == "blackrock"
Provides-Extra: cellexplorer
Requires-Dist: pymatreader>=0.0.32; extra == "cellexplorer"
Requires-Dist: neuroconv[ecephys_minimal]; extra == "cellexplorer"
Provides-Extra: edf
Requires-Dist: pyedflib>=0.1.36; extra == "edf"
Requires-Dist: neuroconv[ecephys_minimal]; extra == "edf"
Provides-Extra: intan
Requires-Dist: neuroconv[ecephys_minimal]; extra == "intan"
Provides-Extra: kilosort
Requires-Dist: neuroconv[ecephys_minimal]; extra == "kilosort"
Provides-Extra: maxwell
Requires-Dist: neuroconv[ecephys_minimal]; extra == "maxwell"
Provides-Extra: mcsraw
Requires-Dist: neuroconv[ecephys_minimal]; extra == "mcsraw"
Provides-Extra: mearec
Requires-Dist: neuroconv[ecephys_minimal]; extra == "mearec"
Requires-Dist: MEArec>=1.8.0; extra == "mearec"
Requires-Dist: setuptools; python_version >= "3.12" and extra == "mearec"
Provides-Extra: neuralynx
Requires-Dist: neuroconv[ecephys_minimal]; extra == "neuralynx"
Requires-Dist: natsort>=7.1.1; extra == "neuralynx"
Provides-Extra: neuroscope
Requires-Dist: neuroconv[ecephys_minimal]; extra == "neuroscope"
Requires-Dist: lxml>=4.6.5; extra == "neuroscope"
Provides-Extra: openephys
Requires-Dist: neuroconv[ecephys_minimal]; extra == "openephys"
Requires-Dist: lxml>=4.9.4; extra == "openephys"
Provides-Extra: phy
Requires-Dist: neuroconv[ecephys_minimal]; extra == "phy"
Provides-Extra: plexon
Requires-Dist: neuroconv[ecephys_minimal]; extra == "plexon"
Provides-Extra: plexon2
Requires-Dist: neuroconv[ecephys_minimal]; extra == "plexon2"
Requires-Dist: zugbruecke>=0.2.1; platform_system != "Windows" and extra == "plexon2"
Provides-Extra: spike2
Requires-Dist: neuroconv[ecephys_minimal]; extra == "spike2"
Requires-Dist: sonpy>=1.7.1; (python_version == "3.9" and platform_system != "Darwin") and extra == "spike2"
Provides-Extra: spikegadgets
Requires-Dist: neuroconv[ecephys_minimal]; extra == "spikegadgets"
Provides-Extra: spikeglx
Requires-Dist: neuroconv[ecephys_minimal]; extra == "spikeglx"
Requires-Dist: probeinterface>=0.3.1; extra == "spikeglx"
Requires-Dist: ndx-events==0.2.1; extra == "spikeglx"
Provides-Extra: tdt
Requires-Dist: neuroconv[ecephys_minimal]; extra == "tdt"
Provides-Extra: whitematter
Requires-Dist: neuroconv[ecephys_minimal]; extra == "whitematter"
Provides-Extra: ecephys
Requires-Dist: neuroconv[alphaomega]; extra == "ecephys"
Requires-Dist: neuroconv[axon]; extra == "ecephys"
Requires-Dist: neuroconv[axona]; extra == "ecephys"
Requires-Dist: neuroconv[biocam]; extra == "ecephys"
Requires-Dist: neuroconv[blackrock]; extra == "ecephys"
Requires-Dist: neuroconv[cellexplorer]; extra == "ecephys"
Requires-Dist: neuroconv[edf]; extra == "ecephys"
Requires-Dist: neuroconv[intan]; extra == "ecephys"
Requires-Dist: neuroconv[kilosort]; extra == "ecephys"
Requires-Dist: neuroconv[maxwell]; extra == "ecephys"
Requires-Dist: neuroconv[mcsraw]; extra == "ecephys"
Requires-Dist: neuroconv[mearec]; extra == "ecephys"
Requires-Dist: neuroconv[neuralynx]; extra == "ecephys"
Requires-Dist: neuroconv[neuroscope]; extra == "ecephys"
Requires-Dist: neuroconv[openephys]; extra == "ecephys"
Requires-Dist: neuroconv[phy]; extra == "ecephys"
Requires-Dist: neuroconv[plexon]; extra == "ecephys"
Requires-Dist: neuroconv[plexon2]; extra == "ecephys"
Requires-Dist: neuroconv[spike2]; extra == "ecephys"
Requires-Dist: neuroconv[spikegadgets]; extra == "ecephys"
Requires-Dist: neuroconv[spikeglx]; extra == "ecephys"
Requires-Dist: neuroconv[tdt]; extra == "ecephys"
Requires-Dist: neuroconv[whitematter]; extra == "ecephys"
Provides-Extra: abf
Requires-Dist: ndx-dandi-icephys>=0.4.0; extra == "abf"
Requires-Dist: neo>=0.13.2; extra == "abf"
Provides-Extra: icephys
Requires-Dist: neuroconv[abf]; extra == "icephys"
Provides-Extra: image
Requires-Dist: pillow>=10.0.0; extra == "image"
Provides-Extra: fiber-photometry
Requires-Dist: ndx-fiber-photometry>=0.2.2; extra == "fiber-photometry"
Provides-Extra: ophys-minimal
Requires-Dist: roiextractors>=0.7.2; extra == "ophys-minimal"
Provides-Extra: brukertiff
Requires-Dist: neuroconv[ophys_minimal]; extra == "brukertiff"
Requires-Dist: tifffile>=2023.3.21; extra == "brukertiff"
Requires-Dist: natsort; extra == "brukertiff"
Provides-Extra: caiman
Requires-Dist: neuroconv[ophys_minimal]; extra == "caiman"
Requires-Dist: scipy; extra == "caiman"
Provides-Extra: cnmfe
Requires-Dist: neuroconv[ophys_minimal]; extra == "cnmfe"
Requires-Dist: scipy; extra == "cnmfe"
Provides-Extra: extract
Requires-Dist: neuroconv[ophys_minimal]; extra == "extract"
Provides-Extra: minian
Requires-Dist: neuroconv[ophys_minimal]; extra == "minian"
Provides-Extra: femtonics
Requires-Dist: neuroconv[ophys_minimal]; extra == "femtonics"
Provides-Extra: hdf5
Requires-Dist: neuroconv[hdf5imaging]; extra == "hdf5"
Provides-Extra: hdf5imaging
Requires-Dist: neuroconv[ophys_minimal]; extra == "hdf5imaging"
Provides-Extra: inscopix
Requires-Dist: isx>=2.0; ((sys_platform != "darwin" or platform_machine != "arm64") and python_version < "3.13") and extra == "inscopix"
Requires-Dist: neuroconv[ophys_minimal]; extra == "inscopix"
Provides-Extra: micromanagertiff
Requires-Dist: neuroconv[ophys_minimal]; extra == "micromanagertiff"
Requires-Dist: tifffile>=2023.3.21; extra == "micromanagertiff"
Provides-Extra: miniscope
Requires-Dist: natsort>=8.3.1; extra == "miniscope"
Requires-Dist: ndx-miniscope>=0.5.1; extra == "miniscope"
Requires-Dist: neuroconv[ophys_minimal]; extra == "miniscope"
Requires-Dist: neuroconv[video]; extra == "miniscope"
Provides-Extra: sbx
Requires-Dist: neuroconv[scanbox]; extra == "sbx"
Provides-Extra: scanbox
Requires-Dist: neuroconv[ophys_minimal]; extra == "scanbox"
Provides-Extra: scanimage
Requires-Dist: neuroconv[ophys_minimal]; extra == "scanimage"
Requires-Dist: natsort; extra == "scanimage"
Requires-Dist: tifffile>=2023.3.21; extra == "scanimage"
Provides-Extra: scanimage-legacy
Requires-Dist: neuroconv[ophys_minimal]; extra == "scanimage-legacy"
Requires-Dist: scanimage-tiff-reader>=1.4.1; extra == "scanimage-legacy"
Provides-Extra: sima
Requires-Dist: neuroconv[ophys_minimal]; extra == "sima"
Provides-Extra: suite2p
Requires-Dist: natsort; extra == "suite2p"
Requires-Dist: neuroconv[ophys_minimal]; extra == "suite2p"
Provides-Extra: tdt-fp
Requires-Dist: neuroconv[fiber_photometry]; extra == "tdt-fp"
Requires-Dist: tdt; extra == "tdt-fp"
Provides-Extra: thor
Requires-Dist: neuroconv[ophys_minimal]; extra == "thor"
Requires-Dist: tifffile>=2023.3.21; extra == "thor"
Provides-Extra: tiff
Requires-Dist: neuroconv[ophys_minimal]; extra == "tiff"
Requires-Dist: tifffile>=2018.10.18; extra == "tiff"
Provides-Extra: ophys
Requires-Dist: neuroconv[brukertiff]; extra == "ophys"
Requires-Dist: neuroconv[caiman]; extra == "ophys"
Requires-Dist: neuroconv[cnmfe]; extra == "ophys"
Requires-Dist: neuroconv[extract]; extra == "ophys"
Requires-Dist: neuroconv[femtonics]; extra == "ophys"
Requires-Dist: neuroconv[inscopix]; extra == "ophys"
Requires-Dist: neuroconv[hdf5imaging]; extra == "ophys"
Requires-Dist: neuroconv[micromanagertiff]; extra == "ophys"
Requires-Dist: neuroconv[miniscope]; extra == "ophys"
Requires-Dist: neuroconv[scanbox]; extra == "ophys"
Requires-Dist: neuroconv[scanimage]; extra == "ophys"
Requires-Dist: neuroconv[sima]; extra == "ophys"
Requires-Dist: neuroconv[suite2p]; extra == "ophys"
Requires-Dist: neuroconv[tdt_fp]; extra == "ophys"
Requires-Dist: neuroconv[thor]; extra == "ophys"
Requires-Dist: neuroconv[tiff]; extra == "ophys"
Requires-Dist: neuroconv[scanimage_legacy]; extra == "ophys"
Provides-Extra: full
Requires-Dist: neuroconv[aws]; extra == "full"
Requires-Dist: neuroconv[compressors]; extra == "full"
Requires-Dist: neuroconv[dandi]; extra == "full"
Requires-Dist: neuroconv[behavior]; extra == "full"
Requires-Dist: neuroconv[ecephys]; extra == "full"
Requires-Dist: neuroconv[icephys]; extra == "full"
Requires-Dist: neuroconv[image]; extra == "full"
Requires-Dist: neuroconv[ophys]; extra == "full"
Requires-Dist: neuroconv[text]; extra == "full"
